[
    {
        "CategoryId": 1001,
        "SKUNumber": 100001,
        "ProductTitle": "Diesel Mens Smartwatch with Leather Strap DZT2009",
        "InStockQty": 20
    }, {
        "CategoryId": 1001,
        "SKUNumber": 100002,
        "ProductTitle": "Samsung Galaxy Watch Active 40mm Silver",
        "InStockQty": 30
    },  {
        "CategoryId": 1002,
        "SKUNumber": 100003,
        "ProductTitle": "Apple iphone XS",
        "InStockQty": 20
    }, {
        "CategoryId": 1002,
        "SKUNumber": 100004,
        "ProductTitle": "Apple iphone X",
        "InStockQty": 30
    },  {
        "CategoryId": 1003,
        "SKUNumber": 100005,
        "ProductTitle": "Maharaja Furnitures",
        "InStockQty": 20
    }, {
        "CategoryId": 1003,
        "SKUNumber": 100006,
        "ProductTitle": "Royal Oak Bed Lamps",
        "InStockQty": 30
    }
]